MANIFEST.in
setup.py
adminboost/__init__.py
adminboost/preview.py
adminboost/media/adminboost/jquery-1.4.2.min.js
adminboost/media/adminboost/scripts.js
adminboost/media/adminboost/styles.css
adminboost/media/adminboost/jquery-ui-1.8.4/jquery-ui-1.8.4.min.js
adminboost/media/adminboost/jquery-ui-1.8.4/ui-lightness/jquery-ui-1.8.4.custom.css
adminboost/media/adminboost/jquery-ui-1.8.4/ui-lightness/images/ui-bg_diagonals-thick_18_b81900_40x40.png
adminboost/media/adminboost/jquery-ui-1.8.4/ui-lightness/images/ui-bg_diagonals-thick_20_666666_40x40.png
adminboost/media/adminboost/jquery-ui-1.8.4/ui-lightness/images/ui-bg_flat_10_000000_40x100.png
adminboost/media/adminboost/jquery-ui-1.8.4/ui-lightness/images/ui-bg_glass_100_f6f6f6_1x400.png
adminboost/media/adminboost/jquery-ui-1.8.4/ui-lightness/images/ui-bg_glass_100_fdf5ce_1x400.png
adminboost/media/adminboost/jquery-ui-1.8.4/ui-lightness/images/ui-bg_glass_65_ffffff_1x400.png
adminboost/media/adminboost/jquery-ui-1.8.4/ui-lightness/images/ui-bg_gloss-wave_35_f6a828_500x100.png
adminboost/media/adminboost/jquery-ui-1.8.4/ui-lightness/images/ui-bg_highlight-soft_100_eeeeee_1x100.png
adminboost/media/adminboost/jquery-ui-1.8.4/ui-lightness/images/ui-bg_highlight-soft_75_ffe45c_1x100.png
adminboost/media/adminboost/jquery-ui-1.8.4/ui-lightness/images/ui-icons_222222_256x240.png
adminboost/media/adminboost/jquery-ui-1.8.4/ui-lightness/images/ui-icons_228ef1_256x240.png
adminboost/media/adminboost/jquery-ui-1.8.4/ui-lightness/images/ui-icons_ef8c08_256x240.png
adminboost/media/adminboost/jquery-ui-1.8.4/ui-lightness/images/ui-icons_ffd27a_256x240.png
adminboost/media/adminboost/jquery-ui-1.8.4/ui-lightness/images/ui-icons_ffffff_256x240.png
adminboost/templates/adminboost/sortable_inlines.html
adminboost/templatetags/__init__.py
adminboost/templatetags/adminboost_tags.py
glamkit_adminboost.egg-info/PKG-INFO
glamkit_adminboost.egg-info/SOURCES.txt
glamkit_adminboost.egg-info/dependency_links.txt
glamkit_adminboost.egg-info/not-zip-safe
glamkit_adminboost.egg-info/top_level.txt