Metadata-Version: 1.0
Name: glamkit-adminboost
Version: 0.0.3
Summary: Makes the Django admin even more awesomer
Home-page: http://github.com/glamkit/glamkit-admintools
Author: Julien Phalip
Author-email: julien@interaction.net.au
License: UNKNOWN
Platform: UNKNOWN
Classifier: Development Status :: 4 - Beta
Classifier: Environment :: Web Environment
Classifier: Intended Audience :: Developers
Classifier: License :: OSI Approved :: BSD License
Classifier: Operating System :: OS Independent
Classifier: Programming Language :: Python
Classifier: Framework :: Django
